markets/__init__.py
markets/embeddings.py
markets/imps.py
markets/option_trades.py
markets/stock_trades.py
mktdata/__init__.py
mktdata/optionsdata.py
mktdata/stock_data.py
mktdata/embeddings/__init__.py
mktdata/embeddings/technical_embeds.py
mktdata/feeds/__init__.py
mktdata/feeds/helpers.py
mktdata/feeds/option_data.py
mktdata/feeds/starter.py
mktdata/feeds/stock_data.py
mktdata/feeds/technicals.py
mktdata/models/__init__.py
mktdata-0.1.0.dist-info/METADATA
mktdata-0.1.0.dist-info/WHEEL
mktdata-0.1.0.dist-info/top_level.txt
mktdata-0.1.0.dist-info/RECORD
