Metadata-Version: 2.1
Name: mktdata
Version: 0.1.0
Requires-Dist: absl-py (==2.0.0)
Requires-Dist: aiofiles (==23.2.1)
Requires-Dist: aiohttp (==3.9.5)
Requires-Dist: aiosignal (==1.3.1)
Requires-Dist: annotated-types (==0.6.0)
Requires-Dist: anyio (==3.7.1)
Requires-Dist: appdirs (==1.4.4)
Requires-Dist: asgiref (==3.7.2)
Requires-Dist: astunparse (==1.6.3)
Requires-Dist: async-timeout (==4.0.3)
Requires-Dist: asyncio (==3.4.3)
Requires-Dist: asyncpg (==0.29.0)
Requires-Dist: attrs (==23.1.0)
Requires-Dist: backoff (==2.2.1)
Requires-Dist: bcrypt (==4.0.1)
Requires-Dist: beautifulsoup4 (==4.12.2)
Requires-Dist: bidict (==0.22.1)
Requires-Dist: blinker (==1.7.0)
Requires-Dist: bs4 (==0.0.2)
Requires-Dist: cachetools (==5.3.2)
Requires-Dist: certifi (==2023.7.22)
Requires-Dist: cffi (==1.16.0)
Requires-Dist: chardet (==5.2.0)
Requires-Dist: charset-normalizer (==3.3.1)
Requires-Dist: chroma-hnswlib (==0.7.3)
Requires-Dist: chromadb (==0.4.15)
Requires-Dist: click (==8.1.7)
Requires-Dist: colorama (==0.4.6)
Requires-Dist: coloredlogs (==15.0.1)
Requires-Dist: contourpy (==1.1.1)
Requires-Dist: cycler (==0.12.1)
Requires-Dist: dataclasses-json (==0.6.1)
Requires-Dist: Deprecated (==1.2.14)
Requires-Dist: discord-webhook (==1.3.1)
Requires-Dist: diskcache (==5.6.3)
Requires-Dist: disnake (==2.9.1)
Requires-Dist: distro (==1.8.0)
Requires-Dist: dm-tree (==0.1.8)
Requires-Dist: docutils (==0.20.1)
Requires-Dist: fastapi (==0.104.0)
Requires-Dist: feedparser (==6.0.10)
Requires-Dist: filelock (==3.13.0)
Requires-Dist: FLAML (==2.1.1)
Requires-Dist: Flask (==3.0.2)
Requires-Dist: Flask-Cors (==4.0.0)
Requires-Dist: Flask-SocketIO (==5.3.6)
Requires-Dist: flatbuffers (==23.5.26)
Requires-Dist: fluidsynth (==0.2)
Requires-Dist: fonttools (==4.43.1)
Requires-Dist: frozendict (==2.3.8)
Requires-Dist: frozenlist (==1.4.1)
Requires-Dist: fsspec (==2023.10.0)
Requires-Dist: gast (==0.5.4)
Requires-Dist: git-filter-repo (==2.38.0)
Requires-Dist: google-auth (==2.23.3)
Requires-Dist: google-auth-oauthlib (==1.1.0)
Requires-Dist: google-pasta (==0.2.0)
Requires-Dist: googleapis-common-protos (==1.61.0)
Requires-Dist: greenlet (==3.0.1)
Requires-Dist: grpcio (==1.59.0)
Requires-Dist: h11 (==0.14.0)
Requires-Dist: h2 (==4.1.0)
Requires-Dist: h5py (==3.10.0)
Requires-Dist: hpack (==4.0.0)
Requires-Dist: html5lib (==1.1)
Requires-Dist: httpcore (==1.0.4)
Requires-Dist: httptools (==0.6.1)
Requires-Dist: httpx (==0.27.0)
Requires-Dist: huggingface-hub (==0.17.3)
Requires-Dist: humanfriendly (==10.0)
Requires-Dist: Hypercorn (==0.15.0)
Requires-Dist: hyperframe (==6.0.1)
Requires-Dist: idna (==3.6)
Requires-Dist: importlib-metadata (==6.11.0)
Requires-Dist: importlib-resources (==6.1.0)
Requires-Dist: itsdangerous (==2.1.2)
Requires-Dist: jaraco.classes (==3.3.0)
Requires-Dist: Jinja2 (==3.1.3)
Requires-Dist: joblib (==1.3.2)
Requires-Dist: jsonpatch (==1.33)
Requires-Dist: jsonpickle (==3.0.2)
Requires-Dist: jsonpointer (==2.4)
Requires-Dist: kaleido (==0.2.1)
Requires-Dist: keras (==2.15.0)
Requires-Dist: keyring (==24.2.0)
Requires-Dist: kiwisolver (==1.4.5)
Requires-Dist: kubernetes (==28.1.0)
Requires-Dist: langchain (==0.0.343)
Requires-Dist: langchain-core (==0.0.7)
Requires-Dist: langchain-decorators (==0.2.3)
Requires-Dist: langchain-experimental (==0.0.35)
Requires-Dist: langsmith (==0.0.67)
Requires-Dist: libclang (==16.0.6)
Requires-Dist: lxml (==4.9.3)
Requires-Dist: Markdown (==3.5.1)
Requires-Dist: markdown-it-py (==3.0.0)
Requires-Dist: MarkupSafe (==2.1.3)
Requires-Dist: marshmallow (==3.20.1)
Requires-Dist: matplotlib (==3.8.3)
Requires-Dist: mdurl (==0.1.2)
Requires-Dist: midi2audio (==0.1.1)
Requires-Dist: mingus (==0.6.1)
Requires-Dist: ml-dtypes (==0.2.0)
Requires-Dist: monotonic (==1.6)
Requires-Dist: more-itertools (==10.1.0)
Requires-Dist: mplfinance (==0.12.10b0)
Requires-Dist: mpmath (==1.3.0)
Requires-Dist: multidict (==6.0.4)
Requires-Dist: multitasking (==0.0.11)
Requires-Dist: music21 (==9.1.0)
Requires-Dist: mypy-extensions (==1.0.0)
Requires-Dist: namex (==0.0.7)
Requires-Dist: natsort (==8.4.0)
Requires-Dist: nh3 (==0.2.14)
Requires-Dist: numpy (==1.26.4)
Requires-Dist: oauthlib (==3.2.2)
Requires-Dist: onnxruntime (==1.16.1)
Requires-Dist: openai (==1.30.5)
Requires-Dist: opentelemetry-api (==1.20.0)
Requires-Dist: opentelemetry-exporter-otlp-proto-common (==1.20.0)
Requires-Dist: opentelemetry-exporter-otlp-proto-grpc (==1.20.0)
Requires-Dist: opentelemetry-proto (==1.20.0)
Requires-Dist: opentelemetry-sdk (==1.20.0)
Requires-Dist: opentelemetry-semantic-conventions (==0.41b0)
Requires-Dist: opt-einsum (==3.3.0)
Requires-Dist: orjson (==3.9.10)
Requires-Dist: outcome (==1.3.0.post0)
Requires-Dist: overrides (==7.4.0)
Requires-Dist: packaging (==23.2)
Requires-Dist: pandas (==2.2.2)
Requires-Dist: peewee (==3.17.0)
Requires-Dist: Pillow (==10.1.0)
Requires-Dist: pkginfo (==1.9.6)
Requires-Dist: plotly (==5.20.0)
Requires-Dist: polygon (==1.1.3)
Requires-Dist: polygon-api-client (==1.13.3)
Requires-Dist: posthog (==3.0.2)
Requires-Dist: priority (==2.0.0)
Requires-Dist: promptwatch (==0.3.0)
Requires-Dist: protobuf (==4.23.4)
Requires-Dist: psycopg2 (==2.9.9)
Requires-Dist: pulsar-client (==3.3.0)
Requires-Dist: pyasn1 (==0.5.0)
Requires-Dist: pyasn1-modules (==0.3.0)
Requires-Dist: pycparser (==2.21)
Requires-Dist: pydantic (==2.4.2)
Requires-Dist: pydantic-core (==2.10.1)
Requires-Dist: pygame (==2.5.2)
Requires-Dist: Pygments (==2.16.1)
Requires-Dist: pyparsing (==3.1.1)
Requires-Dist: PyPDF2 (==3.0.1)
Requires-Dist: PyPika (==0.48.9)
Requires-Dist: pyreadline3 (==3.4.1)
Requires-Dist: PySocks (==1.7.1)
Requires-Dist: pytesseract (==0.3.10)
Requires-Dist: python-dateutil (==2.8.2)
Requires-Dist: python-dotenv (==1.0.0)
Requires-Dist: python-engineio (==4.8.0)
Requires-Dist: python-socketio (==5.10.0)
Requires-Dist: pytrends (==4.9.2)
Requires-Dist: pytz (==2023.3.post1)
Requires-Dist: pywin32 (==306)
Requires-Dist: pywin32-ctypes (==0.2.2)
Requires-Dist: PyYAML (==6.0.1)
Requires-Dist: Quart (==0.19.4)
Requires-Dist: readme-renderer (==42.0)
Requires-Dist: regex (==2023.10.3)
Requires-Dist: requests (==2.31.0)
Requires-Dist: requests-oauthlib (==1.3.1)
Requires-Dist: requests-toolbelt (==1.0.0)
Requires-Dist: rfc3986 (==2.0.0)
Requires-Dist: rich (==13.6.0)
Requires-Dist: rsa (==4.9)
Requires-Dist: safetensors (==0.4.1)
Requires-Dist: scipy (==1.11.4)
Requires-Dist: seaborn (==0.13.0)
Requires-Dist: selenium (==4.14.0)
Requires-Dist: sgmllib3k (==1.0.0)
Requires-Dist: simple-websocket (==1.0.0)
Requires-Dist: six (==1.16.0)
Requires-Dist: sniffio (==1.3.0)
Requires-Dist: sortedcontainers (==2.4.0)
Requires-Dist: soupsieve (==2.5)
Requires-Dist: SQLAlchemy (==2.0.22)
Requires-Dist: starlette (==0.27.0)
Requires-Dist: stocksera (==0.1.21)
Requires-Dist: sympy (==1.12)
Requires-Dist: tabulate (==0.9.0)
Requires-Dist: tenacity (==8.2.3)
Requires-Dist: tensorboard (==2.15.1)
Requires-Dist: tensorboard-data-server (==0.7.2)
Requires-Dist: tensorflow (==2.15.0)
Requires-Dist: tensorflow-estimator (==2.15.0)
Requires-Dist: tensorflow-intel (==2.15.0)
Requires-Dist: tensorflow-io-gcs-filesystem (==0.31.0)
Requires-Dist: termcolor (==2.3.0)
Requires-Dist: tiktoken (==0.5.1)
Requires-Dist: tokenizers (==0.14.1)
Requires-Dist: tqdm (==4.66.1)
Requires-Dist: transformers (==4.35.2)
Requires-Dist: trio (==0.22.2)
Requires-Dist: trio-websocket (==0.11.1)
Requires-Dist: twine (==4.0.2)
Requires-Dist: typer (==0.9.0)
Requires-Dist: typing-inspect (==0.9.0)
Requires-Dist: typing-extensions (==4.9.0)
Requires-Dist: tzdata (==2023.3)
Requires-Dist: urllib3 (==1.26.18)
Requires-Dist: uvicorn (==0.23.2)
Requires-Dist: waitress (==2.1.2)
Requires-Dist: watchfiles (==0.21.0)
Requires-Dist: webcolors (==1.13)
Requires-Dist: webencodings (==0.5.1)
Requires-Dist: websocket-client (==1.6.4)
Requires-Dist: websockets (==12.0)
Requires-Dist: Werkzeug (==3.0.1)
Requires-Dist: wrapt (==1.14.1)
Requires-Dist: wsproto (==1.2.0)
Requires-Dist: yarl (==1.9.4)
Requires-Dist: yfinance (==0.2.32)
Requires-Dist: zipp (==3.17.0)
